{
  "month": "202505",
  "schemas": [
    {
      "table": "PREDISPATCH_REGION_SOLUTION",
      "month": "202505",
      "columns": [
        {
          "name": "PREDISPATCHSEQNO",
          "ty": "FLOAT",
          "format": "EXTERNAL"
        },
        {
          "name": "RUNNO",
          "ty": "FLOAT",
          "format": "EXTERNAL"
        },
        {
          "name": "REGIONID",
          "ty": "utf8",
          "format": null
        },
        {
          "name": "PERIODID",
          "ty": "FLOAT",
          "format": "EXTERNAL"
        },
        {
          "name": "INTERVENTION",
          "ty": "FLOAT",
          "format": "EXTERNAL"
        },
        {
          "name": "TOTALDEMAND",
          "ty": "FLOAT",
          "format": "EXTERNAL"
        },
        {
          "name": "AVAILABLEGENERATION",
          "ty": "FLOAT",
          "format": "EXTERNAL"
        },
        {
          "name": "AVAILABLELOAD",
          "ty": "FLOAT",
          "format": "EXTERNAL"
        },
        {
          "name": "DEMANDFORECAST",
          "ty": "FLOAT",
          "format": "EXTERNAL"
        },
        {
          "name": "DISPATCHABLEGENERATION",
          "ty": "FLOAT",
          "format": "EXTERNAL"
        },
        {
          "name": "DISPATCHABLELOAD",
          "ty": "FLOAT",
          "format": "EXTERNAL"
        },
        {
          "name": "NETINTERCHANGE",
          "ty": "FLOAT",
          "format": "EXTERNAL"
        },
        {
          "name": "EXCESSGENERATION",
          "ty": "FLOAT",
          "format": "EXTERNAL"
        },
        {
          "name": "LOWER5MINDISPATCH",
          "ty": "utf8",
          "format": null
        },
        {
          "name": "LOWER5MINIMPORT",
          "ty": "utf8",
          "format": null
        },
        {
          "name": "LOWER5MINLOCALDISPATCH",
          "ty": "FLOAT",
          "format": "EXTERNAL"
        },
        {
          "name": "LOWER5MINLOCALPRICE",
          "ty": "utf8",
          "format": null
        },
        {
          "name": "LOWER5MINLOCALREQ",
          "ty": "utf8",
          "format": null
        },
        {
          "name": "LOWER5MINPRICE",
          "ty": "utf8",
          "format": null
        },
        {
          "name": "LOWER5MINREQ",
          "ty": "utf8",
          "format": null
        },
        {
          "name": "LOWER5MINSUPPLYPRICE",
          "ty": "utf8",
          "format": null
        },
        {
          "name": "LOWER60SECDISPATCH",
          "ty": "utf8",
          "format": null
        },
        {
          "name": "LOWER60SECIMPORT",
          "ty": "utf8",
          "format": null
        },
        {
          "name": "LOWER60SECLOCALDISPATCH",
          "ty": "FLOAT",
          "format": "EXTERNAL"
        },
        {
          "name": "LOWER60SECLOCALPRICE",
          "ty": "utf8",
          "format": null
        },
        {
          "name": "LOWER60SECLOCALREQ",
          "ty": "utf8",
          "format": null
        },
        {
          "name": "LOWER60SECPRICE",
          "ty": "utf8",
          "format": null
        },
        {
          "name": "LOWER60SECREQ",
          "ty": "utf8",
          "format": null
        },
        {
          "name": "LOWER60SECSUPPLYPRICE",
          "ty": "utf8",
          "format": null
        },
        {
          "name": "LOWER6SECDISPATCH",
          "ty": "utf8",
          "format": null
        },
        {
          "name": "LOWER6SECIMPORT",
          "ty": "utf8",
          "format": null
        },
        {
          "name": "LOWER6SECLOCALDISPATCH",
          "ty": "FLOAT",
          "format": "EXTERNAL"
        },
        {
          "name": "LOWER6SECLOCALPRICE",
          "ty": "utf8",
          "format": null
        },
        {
          "name": "LOWER6SECLOCALREQ",
          "ty": "utf8",
          "format": null
        },
        {
          "name": "LOWER6SECPRICE",
          "ty": "utf8",
          "format": null
        },
        {
          "name": "LOWER6SECREQ",
          "ty": "utf8",
          "format": null
        },
        {
          "name": "LOWER6SECSUPPLYPRICE",
          "ty": "utf8",
          "format": null
        },
        {
          "name": "RAISE5MINDISPATCH",
          "ty": "utf8",
          "format": null
        },
        {
          "name": "RAISE5MINIMPORT",
          "ty": "utf8",
          "format": null
        },
        {
          "name": "RAISE5MINLOCALDISPATCH",
          "ty": "FLOAT",
          "format": "EXTERNAL"
        },
        {
          "name": "RAISE5MINLOCALPRICE",
          "ty": "utf8",
          "format": null
        },
        {
          "name": "RAISE5MINLOCALREQ",
          "ty": "utf8",
          "format": null
        },
        {
          "name": "RAISE5MINPRICE",
          "ty": "utf8",
          "format": null
        },
        {
          "name": "RAISE5MINREQ",
          "ty": "utf8",
          "format": null
        },
        {
          "name": "RAISE5MINSUPPLYPRICE",
          "ty": "utf8",
          "format": null
        },
        {
          "name": "RAISE60SECDISPATCH",
          "ty": "utf8",
          "format": null
        },
        {
          "name": "RAISE60SECIMPORT",
          "ty": "utf8",
          "format": null
        },
        {
          "name": "RAISE60SECLOCALDISPATCH",
          "ty": "FLOAT",
          "format": "EXTERNAL"
        },
        {
          "name": "RAISE60SECLOCALPRICE",
          "ty": "utf8",
          "format": null
        },
        {
          "name": "RAISE60SECLOCALREQ",
          "ty": "utf8",
          "format": null
        },
        {
          "name": "RAISE60SECPRICE",
          "ty": "utf8",
          "format": null
        },
        {
          "name": "RAISE60SECREQ",
          "ty": "utf8",
          "format": null
        },
        {
          "name": "RAISE60SECSUPPLYPRICE",
          "ty": "utf8",
          "format": null
        },
        {
          "name": "RAISE6SECDISPATCH",
          "ty": "utf8",
          "format": null
        },
        {
          "name": "RAISE6SECIMPORT",
          "ty": "utf8",
          "format": null
        },
        {
          "name": "RAISE6SECLOCALDISPATCH",
          "ty": "FLOAT",
          "format": "EXTERNAL"
        },
        {
          "name": "RAISE6SECLOCALPRICE",
          "ty": "utf8",
          "format": null
        },
        {
          "name": "RAISE6SECLOCALREQ",
          "ty": "utf8",
          "format": null
        },
        {
          "name": "RAISE6SECPRICE",
          "ty": "utf8",
          "format": null
        },
        {
          "name": "RAISE6SECREQ",
          "ty": "utf8",
          "format": null
        },
        {
          "name": "RAISE6SECSUPPLYPRICE",
          "ty": "utf8",
          "format": null
        },
        {
          "name": "LASTCHANGED",
          "ty": "DATE",
          "format": "\"yyyy/mm/dd hh24:mi:ss\""
        },
        {
          "name": "DATETIME",
          "ty": "DATE",
          "format": "\"yyyy/mm/dd hh24:mi:ss\""
        },
        {
          "name": "INITIALSUPPLY",
          "ty": "FLOAT",
          "format": "EXTERNAL"
        },
        {
          "name": "CLEAREDSUPPLY",
          "ty": "FLOAT",
          "format": "EXTERNAL"
        },
        {
          "name": "LOWERREGIMPORT",
          "ty": "utf8",
          "format": null
        },
        {
          "name": "LOWERREGLOCALDISPATCH",
          "ty": "FLOAT",
          "format": "EXTERNAL"
        },
        {
          "name": "LOWERREGLOCALREQ",
          "ty": "utf8",
          "format": null
        },
        {
          "name": "LOWERREGREQ",
          "ty": "utf8",
          "format": null
        },
        {
          "name": "RAISEREGIMPORT",
          "ty": "utf8",
          "format": null
        },
        {
          "name": "RAISEREGLOCALDISPATCH",
          "ty": "FLOAT",
          "format": "EXTERNAL"
        },
        {
          "name": "RAISEREGLOCALREQ",
          "ty": "utf8",
          "format": null
        },
        {
          "name": "RAISEREGREQ",
          "ty": "utf8",
          "format": null
        },
        {
          "name": "RAISE5MINLOCALVIOLATION",
          "ty": "utf8",
          "format": null
        },
        {
          "name": "RAISEREGLOCALVIOLATION",
          "ty": "utf8",
          "format": null
        },
        {
          "name": "RAISE60SECLOCALVIOLATION",
          "ty": "utf8",
          "format": null
        },
        {
          "name": "RAISE6SECLOCALVIOLATION",
          "ty": "utf8",
          "format": null
        },
        {
          "name": "LOWER5MINLOCALVIOLATION",
          "ty": "utf8",
          "format": null
        },
        {
          "name": "LOWERREGLOCALVIOLATION",
          "ty": "utf8",
          "format": null
        },
        {
          "name": "LOWER60SECLOCALVIOLATION",
          "ty": "utf8",
          "format": null
        },
        {
          "name": "LOWER6SECLOCALVIOLATION",
          "ty": "utf8",
          "format": null
        },
        {
          "name": "RAISE5MINVIOLATION",
          "ty": "utf8",
          "format": null
        },
        {
          "name": "RAISEREGVIOLATION",
          "ty": "utf8",
          "format": null
        },
        {
          "name": "RAISE60SECVIOLATION",
          "ty": "utf8",
          "format": null
        },
        {
          "name": "RAISE6SECVIOLATION",
          "ty": "utf8",
          "format": null
        },
        {
          "name": "LOWER5MINVIOLATION",
          "ty": "utf8",
          "format": null
        },
        {
          "name": "LOWERREGVIOLATION",
          "ty": "utf8",
          "format": null
        },
        {
          "name": "LOWER60SECVIOLATION",
          "ty": "utf8",
          "format": null
        },
        {
          "name": "LOWER6SECVIOLATION",
          "ty": "utf8",
          "format": null
        },
        {
          "name": "RAISE6SECACTUALAVAILABILITY",
          "ty": "FLOAT",
          "format": "EXTERNAL"
        },
        {
          "name": "RAISE60SECACTUALAVAILABILITY",
          "ty": "FLOAT",
          "format": "EXTERNAL"
        },
        {
          "name": "RAISE5MINACTUALAVAILABILITY",
          "ty": "FLOAT",
          "format": "EXTERNAL"
        },
        {
          "name": "RAISEREGACTUALAVAILABILITY",
          "ty": "FLOAT",
          "format": "EXTERNAL"
        },
        {
          "name": "LOWER6SECACTUALAVAILABILITY",
          "ty": "FLOAT",
          "format": "EXTERNAL"
        },
        {
          "name": "LOWER60SECACTUALAVAILABILITY",
          "ty": "FLOAT",
          "format": "EXTERNAL"
        },
        {
          "name": "LOWER5MINACTUALAVAILABILITY",
          "ty": "FLOAT",
          "format": "EXTERNAL"
        },
        {
          "name": "LOWERREGACTUALAVAILABILITY",
          "ty": "FLOAT",
          "format": "EXTERNAL"
        },
        {
          "name": "DECAVAILABILITY",
          "ty": "FLOAT",
          "format": "EXTERNAL"
        },
        {
          "name": "LORSURPLUS",
          "ty": "utf8",
          "format": null
        },
        {
          "name": "LRCSURPLUS",
          "ty": "utf8",
          "format": null
        },
        {
          "name": "TOTALINTERMITTENTGENERATION",
          "ty": "FLOAT",
          "format": "EXTERNAL"
        },
        {
          "name": "DEMAND_AND_NONSCHEDGEN",
          "ty": "FLOAT",
          "format": "EXTERNAL"
        },
        {
          "name": "UIGF",
          "ty": "FLOAT",
          "format": "EXTERNAL"
        },
        {
          "name": "SEMISCHEDULE_CLEAREDMW",
          "ty": "FLOAT",
          "format": "EXTERNAL"
        },
        {
          "name": "SEMISCHEDULE_COMPLIANCEMW",
          "ty": "FLOAT",
          "format": "EXTERNAL"
        },
        {
          "name": "SS_SOLAR_UIGF",
          "ty": "FLOAT",
          "format": "EXTERNAL"
        },
        {
          "name": "SS_WIND_UIGF",
          "ty": "FLOAT",
          "format": "EXTERNAL"
        },
        {
          "name": "SS_SOLAR_CLEAREDMW",
          "ty": "FLOAT",
          "format": "EXTERNAL"
        },
        {
          "name": "SS_WIND_CLEAREDMW",
          "ty": "FLOAT",
          "format": "EXTERNAL"
        },
        {
          "name": "SS_SOLAR_COMPLIANCEMW",
          "ty": "FLOAT",
          "format": "EXTERNAL"
        },
        {
          "name": "SS_WIND_COMPLIANCEMW",
          "ty": "FLOAT",
          "format": "EXTERNAL"
        },
        {
          "name": "WDR_INITIALMW",
          "ty": "FLOAT",
          "format": "EXTERNAL"
        },
        {
          "name": "WDR_AVAILABLE",
          "ty": "FLOAT",
          "format": "EXTERNAL"
        },
        {
          "name": "WDR_DISPATCHED",
          "ty": "FLOAT",
          "format": "EXTERNAL"
        },
        {
          "name": "LOWER1SECLOCALDISPATCH",
          "ty": "FLOAT",
          "format": "EXTERNAL"
        },
        {
          "name": "RAISE1SECLOCALDISPATCH",
          "ty": "FLOAT",
          "format": "EXTERNAL"
        },
        {
          "name": "RAISE1SECACTUALAVAILABILITY",
          "ty": "FLOAT",
          "format": "EXTERNAL"
        },
        {
          "name": "LOWER1SECACTUALAVAILABILITY",
          "ty": "FLOAT",
          "format": "EXTERNAL"
        },
        {
          "name": "SS_SOLAR_AVAILABILITY",
          "ty": "FLOAT",
          "format": "EXTERNAL"
        },
        {
          "name": "SS_WIND_AVAILABILITY",
          "ty": "FLOAT",
          "format": "EXTERNAL"
        },
        {
          "name": "BDU_ENERGY_STORAGE",
          "ty": "utf8",
          "format": null
        },
        {
          "name": "BDU_MIN_AVAIL",
          "ty": "FLOAT",
          "format": "EXTERNAL"
        },
        {
          "name": "BDU_MAX_AVAIL",
          "ty": "FLOAT",
          "format": "EXTERNAL"
        },
        {
          "name": "BDU_CLEAREDMW_GEN",
          "ty": "FLOAT",
          "format": "EXTERNAL"
        },
        {
          "name": "BDU_CLEAREDMW_LOAD",
          "ty": "FLOAT",
          "format": "EXTERNAL"
        }
      ]
    }
  ]
}